{
  "biomemakeover:biomemakeover/root": {
    "criteria": {
      "enter_dark_forest": "2021-10-02 02:40:20 +0800"
    },
    "done": true
  },
  "minecraft:recipes/transportation/acacia_boat": {
    "criteria": {
      "in_water": "2021-10-02 02:42:00 +0800"
    },
    "done": true
  },
  "minecraft:recipes/transportation/oak_boat": {
    "criteria": {
      "in_water": "2021-10-02 02:42:00 +0800"
    },
    "done": true
  },
  "minecraft:recipes/transportation/dark_oak_boat": {
    "criteria": {
      "in_water": "2021-10-02 02:42:00 +0800"
    },
    "done": true
  },
  "minecraft:recipes/transportation/birch_boat": {
    "criteria": {
      "in_water": "2021-10-02 02:42:00 +0800"
    },
    "done": true
  },
  "minecraft:recipes/building_blocks/emerald_block": {
    "criteria": {
      "has_emerald": "2021-10-02 02:38:37 +0800"
    },
    "done": true
  },
  "minecraft:recipes/transportation/jungle_boat": {
    "criteria": {
      "in_water": "2021-10-02 02:42:00 +0800"
    },
    "done": true
  },
  "minecraft:recipes/transportation/spruce_boat": {
    "criteria": {
      "in_water": "2021-10-02 02:42:00 +0800"
    },
    "done": true
  },
  "minecraft:adventure/adventuring_time": {
    "criteria": {
      "minecraft:dark_forest": "2021-10-02 02:40:20 +0800",
      "minecraft:river": "2021-10-02 02:41:55 +0800",
      "minecraft:swamp": "2021-10-02 02:41:48 +0800",
      "minecraft:plains": "2021-10-02 02:34:00 +0800"
    },
    "done": false
  },
  "DataVersion": 2586
}