{
  "biomemakeover:biomemakeover/root": {
    "criteria": {
      "enter_swamp": "2022-04-13 15:38:02 +0800"
    },
    "done": true
  },
  "minecraft:adventure/adventuring_time": {
    "criteria": {
      "minecraft:forest": "2022-04-13 15:32:52 +0800",
      "minecraft:mountains": "2022-04-13 15:32:25 +0800",
      "minecraft:birch_forest": "2022-04-13 15:33:44 +0800",
      "minecraft:river": "2022-04-13 15:30:26 +0800",
      "minecraft:wooded_mountains": "2022-04-13 15:32:44 +0800",
      "minecraft:wooded_hills": "2022-04-13 15:43:24 +0800",
      "minecraft:stone_shore": "2022-04-13 15:25:49 +0800",
      "minecraft:swamp": "2022-04-13 15:38:02 +0800"
    },
    "done": false
  },
  "DataVersion": 2586
}