{"stats":{"minecraft:dropped":{"cspirit:present_wrapped_red":1},"minecraft:used":{"minecraft:written_book":1},"minecraft:picked_up":{"cspirit:present_wrapped_red":4},"minecraft:custom":{"minecraft:jump":1067,"minecraft:time_since_rest":30876,"minecraft:deaths":3,"minecraft:play_one_minute":145838,"minecraft:crouch_one_cm":4795,"minecraft:damage_taken":1250,"minecraft:leave_game":12,"minecraft:sprint_one_cm":545058,"minecraft:time_since_death":30869,"minecraft:walk_on_water_one_cm":5346,"minecraft:walk_one_cm":481050,"minecraft:sneak_time":814,"minecraft:walk_under_water_one_cm":2267,"minecraft:swim_one_cm":12815,"minecraft:fall_one_cm":24871,"minecraft:drop":1,"minecraft:fly_one_cm":3336854,"minecraft:open_chest":1}},"DataVersion":2586}