{"stats":{"minecraft:dropped":{"minecraft:minecart":1,"cspirit:present_wrapped_red":1},"minecraft:picked_up":{"cspirit:present_wrapped_red":2,"minecraft:emerald":128},"minecraft:custom":{"minecraft:jump":2189,"minecraft:time_since_rest":50020,"minecraft:damage_taken":730,"minecraft:leave_game":5,"minecraft:play_one_minute":228802,"minecraft:crouch_one_cm":129,"minecraft:time_since_death":50019,"minecraft:walk_one_cm":636899,"minecraft:sprint_one_cm":762769,"minecraft:deaths":6,"minecraft:walk_on_water_one_cm":555,"minecraft:sneak_time":216,"minecraft:fall_one_cm":36178,"minecraft:drop":2,"minecraft:fly_one_cm":13735416}},"DataVersion":2586}