{"stats":{"minecraft:picked_up":{"cspirit:present_wrapped_red":1},"minecraft:custom":{"minecraft:jump":177,"minecraft:time_since_rest":2709,"minecraft:deaths":3,"minecraft:crouch_one_cm":4,"minecraft:play_one_minute":21352,"minecraft:damage_taken":470,"minecraft:leave_game":2,"minecraft:sprint_one_cm":46835,"minecraft:walk_on_water_one_cm":375,"minecraft:time_since_death":2706,"minecraft:walk_one_cm":54147,"minecraft:sneak_time":36,"minecraft:walk_under_water_one_cm":668,"minecraft:swim_one_cm":695,"minecraft:boat_one_cm":367153,"minecraft:fall_one_cm":9280,"minecraft:fly_one_cm":331753}},"DataVersion":2586}