{"stats":{"minecraft:picked_up":{"cspirit:present_wrapped_red":6,"minecraft:emerald":36},"minecraft:custom":{"minecraft:jump":2519,"minecraft:time_since_rest":96,"minecraft:damage_taken":350,"minecraft:play_one_minute":133261,"minecraft:crouch_one_cm":1162,"minecraft:leave_game":20,"minecraft:time_since_death":94,"minecraft:sprint_one_cm":311662,"minecraft:walk_one_cm":153909,"minecraft:walk_on_water_one_cm":3148,"minecraft:deaths":3,"minecraft:sneak_time":316,"minecraft:walk_under_water_one_cm":393,"minecraft:fall_one_cm":22022,"minecraft:boat_one_cm":12427,"minecraft:fly_one_cm":4697833}},"DataVersion":2586}