{"stats":{"minecraft:picked_up":{"cspirit:present_wrapped_red":6},"minecraft:custom":{"minecraft:jump":433,"minecraft:time_since_rest":128460,"minecraft:play_one_minute":128460,"minecraft:crouch_one_cm":44,"minecraft:damage_taken":250,"minecraft:leave_game":6,"minecraft:sprint_one_cm":46048,"minecraft:time_since_death":128460,"minecraft:walk_on_water_one_cm":42255,"minecraft:walk_one_cm":659145,"minecraft:sneak_time":615,"minecraft:climb_one_cm":90,"minecraft:walk_under_water_one_cm":39329,"minecraft:fall_one_cm":7157,"minecraft:drop":1,"minecraft:fly_one_cm":5043706,"minecraft:open_chest":1},"minecraft:dropped":{"cspirit:present_wrapped_red":1},"minecraft:used":{"minecraft:written_book":2}},"DataVersion":2586}